chia_puzzles_py/__init__.py
chia_puzzles_py/manage_clvm.py
chia_puzzles_py/programs.py
chia_puzzles_py/tests/__init__.py
chia_puzzles_py/tests/test_import.py
chia_puzzles_py-0.20.3.dist-info/METADATA
chia_puzzles_py-0.20.3.dist-info/WHEEL
chia_puzzles_py-0.20.3.dist-info/licenses/LICENSE
chia_puzzles_py-0.20.3.dist-info/RECORD
