Metadata-Version: 2.4
Name: chia_puzzles_py
Version: 0.20.3
Summary: A collection of the currently deployed ChiaLisp puzzles.
License-File: LICENSE
Author: Matt Howard
Author-email: matt@chia.net
Requires-Python: >=3.8,<4.0
Classifier: Programming Language :: Python :: 3
Classifier: Programming Language :: Python :: 3.8
Classifier: Programming Language :: Python :: 3.9
Classifier: Programming Language :: Python :: 3.10
Classifier: Programming Language :: Python :: 3.11
Classifier: Programming Language :: Python :: 3.12
Classifier: Programming Language :: Python :: 3.13
Classifier: Programming Language :: Python :: 3.14
Requires-Dist: clvm-rs (>=0.2.3,<0.3.0)
Requires-Dist: clvm-tools-rs (>=0.1.45,<0.2.0)
Requires-Dist: pytest (>=8.3.3,<9.0.0)
